// class version 52.0 (52)
// access flags 0x21
public class com/guiceexample/injection/MyModule extends com/google/inject/AbstractModule  {

  // compiled from: MyModule.java

  // access flags 0x1
  public <init>()V
   L0
    LINENUMBER 17 L0
    ALOAD 0
    INVOKESPECIAL com/google/inject/AbstractModule.<init> ()V
    RETURN
   L1
    LOCALVARIABLE this Lcom/guiceexample/injection/MyModule; L0 L1 0
    MAXSTACK = 1
    MAXLOCALS = 1

  // access flags 0x4
  protected configure()V
   L0
    LINENUMBER 22 L0
    ALOAD 0
    LDC Ljava/lang/String;.class
    INVOKEVIRTUAL com/guiceexample/injection/MyModule.bind (Ljava/lang/Class;)Lcom/google/inject/binder/AnnotatedBindingBuilder;
    LDC "EURUSD"
    INVOKEINTERFACE com/google/inject/binder/AnnotatedBindingBuilder.toInstance (Ljava/lang/Object;)V
   L1
    LINENUMBER 23 L1
    ALOAD 0
    LDC Ljava/util/concurrent/ScheduledExecutorService;.class
    INVOKEVIRTUAL com/guiceexample/injection/MyModule.bind (Ljava/lang/Class;)Lcom/google/inject/binder/AnnotatedBindingBuilder;
    INVOKESTATIC java/util/concurrent/Executors.newSingleThreadScheduledExecutor ()Ljava/util/concurrent/ScheduledExecutorService;
    INVOKEINTERFACE com/google/inject/binder/AnnotatedBindingBuilder.toInstance (Ljava/lang/Object;)V
   L2
    LINENUMBER 24 L2
    RETURN
   L3
    LOCALVARIABLE this Lcom/guiceexample/injection/MyModule; L0 L3 0
    MAXSTACK = 2
    MAXLOCALS = 1

  // access flags 0x1
  public provideQuoteService(Lcom/guiceexample/util/AuditLogger;)Lcom/guiceexample/service/QuoteService;
  @Lcom/google/inject/Provides;()
  @Ljavax/inject/Inject;()
   L0
    LINENUMBER 30 L0
    NEW com/guiceexample/service/YahooQuoteService
    DUP
    ALOAD 1
    INVOKESPECIAL com/guiceexample/service/YahooQuoteService.<init> (Lcom/guiceexample/util/AuditLogger;)V
    ARETURN
   L1
    LOCALVARIABLE this Lcom/guiceexample/injection/MyModule; L0 L1 0
    LOCALVARIABLE auditLogger Lcom/guiceexample/util/AuditLogger; L0 L1 1
    MAXSTACK = 3
    MAXLOCALS = 2
}
